dodotable/__init__.py
dodotable/condition.py
dodotable/exc.py
dodotable/helper.py
dodotable/schema.py
dodotable/util.py
dodotable/environment/__init__.py
dodotable/environment/flask.py
dodotable/templates/cell.html
dodotable/templates/column.html
dodotable/templates/ilike_set.html
dodotable/templates/limit.html
dodotable/templates/linkedcell.html
dodotable/templates/pager.html
dodotable/templates/row.html
dodotable/templates/select_filter.html
dodotable/templates/table.html
dodotable-0.1.3.dist-info/DESCRIPTION.rst
dodotable-0.1.3.dist-info/METADATA
dodotable-0.1.3.dist-info/metadata.json
dodotable-0.1.3.dist-info/RECORD
dodotable-0.1.3.dist-info/top_level.txt
dodotable-0.1.3.dist-info/WHEEL
