Metadata-Version: 2.0
Name: dodotable
Version: 0.1.3
Summary: dodotable
Home-page: https://github.com/spoqa/dodotable
Author: Kang Hyojun
Author-email: ed@spoqa.com
License: MIT
Platform: UNKNOWN
Requires-Dist: setuptools
Requires-Dist: Flask
Requires-Dist: Jinja2
Requires-Dist: SQLAlchemy
Requires-Dist: six (>=1.10.0,<2.0.0)
Provides-Extra: tests
Requires-Dist: lxml; extra == 'tests'
Requires-Dist: pytest (>=2.7.0); extra == 'tests'
Requires-Dist: tox (>=2.1.1); extra == 'tests'
Requires-Dist: import-order; extra == 'tests'
Requires-Dist: flake8; extra == 'tests'
